dataframeXconverter.py
dataframeXconverter-0.0.2.dist-info/LICENSE
dataframeXconverter-0.0.2.dist-info/METADATA
dataframeXconverter-0.0.2.dist-info/WHEEL
dataframeXconverter-0.0.2.dist-info/top_level.txt
dataframeXconverter-0.0.2.dist-info/RECORD
