Metadata-Version: 2.1
Name: dataframeXconverter
Version: 0.0.2
Summary: This package converts dataframe to csv,Html,Xml
Home-page: UNKNOWN
Author: Haridas
Author-email: vrharidas141@gmail.com
License: UNKNOWN
Platform: UNKNOWN
Classifier: Programming Language :: Python :: 3
Classifier: License :: OSI Approved :: MIT License
Classifier: Operating System :: OS Independent
Requires-Dist: pandas
